ctx19/__init__.py
ctx19/parsers.py
ctx19-1.3.dist-info/LICENSE
ctx19-1.3.dist-info/METADATA
ctx19-1.3.dist-info/WHEEL
ctx19-1.3.dist-info/top_level.txt
ctx19-1.3.dist-info/RECORD
