Metadata-Version: 2.1
Name: ctx19
Version: 1.3
Summary: A Python driver for Contextual19 markup language
Home-page: https://github.com/syntpump/contextual19
Author: Syntpump
Author-email: lynnporu@gmail.com
License: UNKNOWN
Project-URL: Syntpump on GitHub, https://github.com/syntpump
Keywords: nlp
Platform: UNKNOWN
Classifier: Development Status :: 5 - Production/Stable
Classifier: Intended Audience :: Developers
Classifier: Intended Audience :: Science/Research
Classifier: License :: OSI Approved :: MIT License
Requires-Python: >3
